lwagents/__init__.py
lwagents/agent.py
lwagents/graph.py
lwagents/logs.py
lwagents/messages.py
lwagents/models.py
lwagents/state.py
lwagents/tools.py
lwagents-2.1.0.dist-info/licenses/LICENSE
lwagents-2.1.0.dist-info/METADATA
lwagents-2.1.0.dist-info/WHEEL
lwagents-2.1.0.dist-info/top_level.txt
lwagents-2.1.0.dist-info/RECORD
