Metadata-Version: 2.4
Name: lwagents
Version: 2.1.0
Summary: A lightweight library for building graph-driven AI agents with tool integration.
Author-email: Henning Gruhl <henning@gruhl.me>
License-Expression: MIT
Project-URL: Homepage, https://github.com/HenningGC/lwagents
Project-URL: Repository, https://github.com/HenningGC/lwagents
Classifier: Programming Language :: Python :: 3
Classifier: Operating System :: OS Independent
Requires-Python: >=3.11
License-File: LICENSE
Requires-Dist: anthropic>=0.70.0
Requires-Dist: openai>=1.59.3
Requires-Dist: pydantic>=2.10.4
Requires-Dist: python-dotenv>=1.0.1
Requires-Dist: typing-extensions>=4.12.2
Dynamic: license-file
